README.md
setup.cfg
setup.py
cli/__init__.py
cli/cli.py
cli/config.py
cli/deploy.py
cli/environment.py
cli/repository.py
cli/server.py
cli/user.py
deploybot_cli.egg-info/PKG-INFO
deploybot_cli.egg-info/SOURCES.txt
deploybot_cli.egg-info/dependency_links.txt
deploybot_cli.egg-info/entry_points.txt
deploybot_cli.egg-info/not-zip-safe
deploybot_cli.egg-info/requires.txt
deploybot_cli.egg-info/top_level.txt