Metadata-Version: 1.0
Name: deploybot-cli
Version: 0.3.2
Summary: Deploybot API Client
Home-page: https://github.com/mrprompt/deploybot-cli
Author: Thiago Paes
Author-email: mrprompt@gmail.com
License: GPL
Keywords: deploy,service,api,client,cli,deploybot,continuous,delivery,cd
Platform: UNKNOWN
